bulkman/__init__.py
bulkman/config.py
bulkman/core.py
bulkman/exceptions.py
bulkman/state.py
bulkman/sync_bridge.py
bulkman/threading.py
bulkman-1.2.2.dist-info/licenses/LICENSE
bulkman-1.2.2.dist-info/METADATA
bulkman-1.2.2.dist-info/WHEEL
bulkman-1.2.2.dist-info/top_level.txt
bulkman-1.2.2.dist-info/RECORD
