Metadata-Version: 2.4
Name: bulkman
Version: 1.2.2
Summary: Bulkhead pattern implementation with Trio for structured concurrency and resilient circuit breaking
Author-email: Farshid Ashouri <farsheed.ashouri@gmail.com>
License-Expression: Apache-2.0
Project-URL: Homepage, https://github.com/rodmena-limited/bulkman
Project-URL: Repository, https://github.com/rodmena-limited/bulkman
Classifier: Development Status :: 4 - Beta
Classifier: Intended Audience :: Developers
Classifier: Programming Language :: Python :: 3
Classifier: Programming Language :: Python :: 3.9
Classifier: Programming Language :: Python :: 3.10
Classifier: Programming Language :: Python :: 3.11
Classifier: Programming Language :: Python :: 3.12
Classifier: Programming Language :: Python :: 3.13
Classifier: Programming Language :: Python :: 3.14
Classifier: Topic :: Software Development :: Libraries :: Python Modules
Classifier: Topic :: System :: Distributed Computing
Classifier: Topic :: System :: Networking
Classifier: Framework :: Trio
Requires-Python: >=3.9
License-File: LICENSE
Requires-Dist: trio>=0.22.0
Requires-Dist: resilient-circuit[postgres]>=0.4.1
Provides-Extra: dev
Requires-Dist: black>=23.0.0; extra == "dev"
Requires-Dist: isort>=5.0.0; extra == "dev"
Requires-Dist: mypy>=1.0.0; extra == "dev"
Requires-Dist: pytest>=7.0.0; extra == "dev"
Requires-Dist: pytest-trio>=0.8.0; extra == "dev"
Requires-Dist: pytest-cov>=4.0.0; extra == "dev"
Requires-Dist: pytest-mock>=3.0.0; extra == "dev"
Requires-Dist: ruff>=0.1.0; extra == "dev"
Dynamic: license-file
